xllamacpp.libs/libgomp-a34b3233.so.1.0.0
xllamacpp-0.2.9.dist-info/WHEEL
xllamacpp-0.2.9.dist-info/top_level.txt
xllamacpp-0.2.9.dist-info/METADATA
xllamacpp-0.2.9.dist-info/RECORD
xllamacpp-0.2.9.dist-info/licenses/LICENSE
xllamacpp/_version.py
xllamacpp/memory.py
xllamacpp/__init__.py
xllamacpp/xllamacpp.abi3.so
