Metadata-Version: 2.4
Name: xllamacpp
Version: 0.2.9
Summary: A Python wrapper of llama.cpp
Author-email: codingl2k1 <codingl2k1@outlook.com>
License: MIT
Requires-Python: >=3.10
License-File: LICENSE
Provides-Extra: test
Requires-Dist: pytest; extra == "test"
Requires-Dist: pytest-cov; extra == "test"
Provides-Extra: all
Requires-Dist: gguf; extra == "all"
Requires-Dist: orjson; extra == "all"
Dynamic: license
Dynamic: license-file
Dynamic: requires-python
